sep005_io_dxd/__init__.py
sep005_io_dxd/dxd.py
sep005_io_dxd-0.0.1.dist-info/METADATA
sep005_io_dxd-0.0.1.dist-info/WHEEL
sep005_io_dxd-0.0.1.dist-info/top_level.txt
sep005_io_dxd-0.0.1.dist-info/RECORD
