Metadata-Version: 2.1
Name: sep005-io-dxd
Version: 0.0.1
Summary: Dewesoft DXD file read functions compliant with SDyPy SEP005
Home-page: https://github.com/OWI-Lab
Author: Wout Weijtjens
Author-email: wout.weijtjens@vub.be
Maintainer: Wout Weijtjens
Maintainer-email: wout.weijtjens@vub.be
License: MIT license
Keywords: io,fbgs,SEP005
Classifier: Development Status :: 3 - Alpha
Classifier: Intended Audience :: Developers
Classifier: Programming Language :: Python :: 3.6
